{
    "동수칸": "UCVJT18d9wSCnDUdnJ9ycO7Q", 
    "견자희": "UCBvkQFBskQR9NeOoDYR8ckA", 
    "룩삼": "UCQLfdihF1WwbuVcgJq6x6Iw", 
    "우왁굳": "UCBkyj16n2snkRg1BAzpovXQ", 
    "옥냥이": "UCcdlIcleb4oIK6of1ugSJ7w", 
    "와나나": "UC-5acDjU6XFWu-__G17V_YQ", 
    "철면수심": "UCy-H-BPCHctNmUb80MeapvQ", 
    "테스터훈": "UCUbOogiD-4PKDqaJfSOTC0g", 
    "기무기훈": "UCRmstH7h-AZpmkBoTa6QoVw", 
    "흐쟁이덩": "UCWOx-QEaE9bjGHhO5J1mgpQ", 
    "김재원": "UCta_NRwnsUaew0t3VNxBNyg", 
    "공혁준": "UCUXYT0CqvBx1ZysmxSW7EDQ", 
    "우정잉": "UCW945UjEs6Jm3rVNvPEALdg", 
    "플러리": "UCdZGwKwvi_i5BLvFzCj4FXw", 
    "홍방장": "UCHxrU6bjWrnBfmReUAeztcw", 
    "머독": "UC-Zedn7a_RJyb5hUQ-aGZog", 
    "소니쇼": "UC141BuVRzSSXJX33Am9yxEA", 
    "레니아워": "UC8ZHpQe-KZFKkC7RrYsLInQ",
    "케인" : "UC0aKwoKNeqBaUwiEXmkQaGQ",
    "형독방송" : "UCJDEss5wA1ddrCBC40giO8A",
    "초승달" : "UCxx7UvIhPkEQxaplaWS2hLg",
    "풍월량" : "UCyHvSKT_bLDYpkv1JjjsLAg",
    "얍얍" : "UCnb4EuP3C0dxeika3b-bnXA",
    "쉐리" : "UClDbuB3bgZYVIaN3534c_ew",
    "코렛트" : "UCvmHDocKuL6MVx1qRgqLV9g",
    "탬탬버린" : "UCCA8UWUW80iHqK9ymdjRwPg",
    "heavyRainism" : "UC0RFuGLQPD6Vi51KMtU_ERA",
    "김진우" : "UCweizAaKFQrSEYnleVOZqTA",
    "갱생레바" : "UCFqvKeEMGrJfJPEOafy1v4Q",
    "빡겜러" : "UCS5OzRgYPzc_bfveKFc4mNw",
    "푸사" : "UCGlbF_ycg31KebOOhkryVSQ",
    "제갈량" : "UCNFohBYBPwTOZi8TC8GauGQ",
    "루시아" : "UC-HN79vzkmv-tPdfK08-NVg",
    "서새봄냥" : "UCYtNOIg99pgGcrE4Uo44OdQ",
    "김블루" : "UCNzcxCN_Hh_lu5RCSFXKgGQ",
    "텔론_" : "UCl4nBkmJCDs6RR8uWldAqLA",
    "피유" : "UCcKITUR4mDL0BSugm4nn66w",
    "샤이__" : "UCBo3r_IAd1EiFGe1x7GgTLw",
    "캡틴잭" : "UC7wtTnMorJi_d93lb_P2Xow",
    "소풍왔니" : "UC5qsXOIsLbkEIP4DI7xWOlg",
    "짬타수아" : "UCNoSlvimHmdOgtHOCNjj7ew",
    "마스카" : "UCxWCCG3LkSrVqnD809feFxg",
    "백설양" : "UCQPPzb7y4aJz6VV1F3v066g",
    "서나랑" : "UCfPC-CKqhZxIS5zdQxmln3Q",
    "아빠킹" : "UChfs1dQ5phBDBWZJ1hHLbUA",
    "함군" : "UCtg0O--13mG02APhQH1GWJw",
    "김나성" : "UCRjQDHdSObypL53Lez8XTBA",
    "왈도쿤" : "UC-S8JFhLkQ5enhB70c2CYIw",
    "닥터준_라인하르트" : "UCOY3LbxXxCd8SykBvcVJlzg",
    "악녀" : "UCvXoedkUpd2frzLnZgpx1zw",
    "똘킹" : "UCnQRkIhRmXrxGrK4-8n-lVw",
    "가이코" : "UCYWW_lthmN8cvuIaN0G9D6g",
    "안산저격수" : "UC7g2JNSc0SefzMTyc--Nn4w",
    "이초홍" : "UC-jHB5e-6LF-yz0kMCTZWdg",
    "뷜랑" : "UCnBvvlF07eXGFqZmTI3HwdQ",
    "햇살살" : "UCdyWkqyljl1nta21aVXImDg",
    "이선생84" : "UC0TMdsyB2cpzDQ9BqdZjs4Q",
    "노돌리" : "UCNvGiN93jKCp39Jsq31BMmg",
    "김도" : "UC2_VPutZK0o_tG8ca_QrQRA",
    "날게렌" : "UCUEX0L7GHPs95m8S7G6kWVA",
    "충전용" : "UCKlAk0pHPolxxERgP4WAwqw",
    "홍개" : "UCDkQMlfo7GvgvnrkPawW9tg",
    "이춘향" : "UCH-5Xjx6MuEySkb-lAdIEeg",
    "에렌디라" : "UC6xWZn2suKPqAQkidOiMeHg",
    "눈쟁이" : "UCJiv3w22pf4Cgpwxo70MbhQ",
    "치킨쿤": "UCD4PvWa8T2SpKo3Ml6KUpKg",
    "천양" : "UCXOLqHsi_mxJdTIqU7B6OmQ",
    "두칠이" : "UCwDFdWg0nGlEMr4iJnKWqYw",
    "침착맨" : "UCUj6rrhMTR9pipbAWBAMvUQ",
    "김용녀" : "UCXmdpmRnf5WKMssvByY2Elg",
    "아구" : "UCAGUSx1hbPKDqzBZH7bTjiA",
    "오킹" : "UCom6YhUY62jM52nIMjf5_dw",
    "매도우이헌터" : "UC4rp07nTMJb13faNO94lm6A",
    "갓보기" : "UCTwAgFBHg_JPQ-P32xfWVaw",
    "스틸로" : "UCCheyE9MwzDKf8vn5vc-fFA",
    "홍차" : "UCHDCGDooQtHQvAuE20axnzQ",
    "녹두로" : "UC9vz3TBChrJmYbzUo-rqfSg",
    
    "선바" : "UCIPSyiBBm9VtWGj-Q7trkKw",
    "액시스마이콜" : "UC7uKMg7lPdCp4Nm1tLesihQ",
    "우주하마" : "UC2NFRq9s2neD_Ml0tPhNC2Q",
    "고차비" : "UCjZy8afeI-58sPLgJIOmecg",
    "쌍베" : "UCvG7coejM6UD_rOnuDdIoFw",
    "다주" : "UCawY6uW94r1JcBuOTqHDfow",
    
    "중괄호" : "UC4R_mbbXliNgCUnfQHbQWgQ",
    
    "카라멜" : "UCiiCuj4h6nkjYIjtimj2N-g",
    "삼식" : "UCMOOio1GZ50OeJT58DGBQCA",
    "삐부" : "UCWbbrLELoBRo-8KG1D9m4HQ",
    "미라지" : "UC73j3rtkjb3qCvC7XZidzmw",
    "인간젤리" : "UCN8hAr9PSgY94RD6u7rZ_ig",
    "태상" : "UCYiaPV-EXQeHrbeQGilEwfg",
    "딩셉션" : "UCl1XENGI2x5vRCnAESPPmcQ",
    "김기열" : "UCf8xJL-CznwfW7W2LO3y_EQ",
    "매드라이프" : "UCj1RW5MrOLh_VrX3yHF_yow",
    "식빵월드" : "UC2IQrKsK1f-cqL--LNBNOrw",
    "긍정인" : "UCAm0pQmaq6dTcH2-qL6RQjQ",
    "연두는말안드뤄" : "UCFRDmLQJItqvkfFFfuTGGVg",
    "보물창고" : "UCRwMczVQ8Jr8_8Dd8o7hPnQ",
    "빅헤드" : "UCAJ-meoCh1TrPZ7La3UpPrw",
    "스피드소닉" : "UCZ058EHycVGJ-iC1EuxEm3Q",
    "김뚜띠" : "UCTZPZo3xuW5k6RkhlVaJ0jQ"
}